clorps/__init__.py
clorps/clorps.py
clorps-0.1.0.dist-info/METADATA
clorps-0.1.0.dist-info/WHEEL
clorps-0.1.0.dist-info/top_level.txt
clorps-0.1.0.dist-info/RECORD
