Metadata-Version: 2.1
Name: clorps
Version: 0.1.0
Summary: CLORPS: A module for CLIP, LPIPS, and ORB based image similarity.
Home-page: https://github.com/vaidatascientist
Author: Vaibhav Gupta
Author-email: vaibhavgupta.ggwp@gmail.com
Classifier: Programming Language :: Python :: 3
Classifier: License :: OSI Approved :: MIT License
Classifier: Operating System :: OS Independent
Requires-Python: >=3.6
Requires-Dist: torch
Requires-Dist: open-clip-torch
Requires-Dist: lpips
Requires-Dist: numpy
Requires-Dist: scikit-learn
Requires-Dist: Pillow
Requires-Dist: opencv-python
